aryan/__init__.py
aryan/application.py
aryan/bot.py
aryan/contact/__init__.py
aryan/contact/anonymous_member.py
aryan/contact/contact.py
aryan/contact/contact_list.py
aryan/contact/contact_or_bot.py
aryan/contact/friend.py
aryan/contact/group.py
aryan/contact/member.py
aryan/contact/normal_member.py
aryan/contact/stranger.py
aryan/contact/user.py
aryan/contact/user_or_bot.py
aryan/event/__init__.py
aryan/event/channel.py
aryan/event/events/__init__.py
aryan/event/events/app.py
aryan/event/events/bot.py
aryan/event/events/friend.py
aryan/event/events/group.py
aryan/event/events/message.py
aryan/event/events/nudge_event.py
aryan/event/events/types.py
aryan/event/listener.py
aryan/message/__init__.py
aryan/message/code/__init__.py
aryan/message/code/codable.py
aryan/message/code/mirai_code.py
aryan/message/data/__init__.py
aryan/message/data/at.py
aryan/message/data/chain.py
aryan/message/data/contrain_single.py
aryan/message/data/face.py
aryan/message/data/image.py
aryan/message/data/message.py
aryan/message/data/plain.py
aryan/message/data/quote.py
aryan/message/data/single_message.py
aryan/message/data/source.py
aryan/message/message_receipt.py
aryan/protocol.py
aryan/utils.py
aryan-0.1.0.dist-info/LICENSE
aryan-0.1.0.dist-info/WHEEL
aryan-0.1.0.dist-info/METADATA
aryan-0.1.0.dist-info/RECORD
