Metadata-Version: 2.1
Name: aryan
Version: 0.1.0
Summary: A small package
Author: qianmo527
Author-email: 2816661524@qq.com
Requires-Python: >=3.9,<4.0
Classifier: Programming Language :: Python :: 3
Classifier: Programming Language :: Python :: 3.10
Classifier: Programming Language :: Python :: 3.9
Requires-Dist: aiohttp (>=3.8.1,<4.0.0)
Requires-Dist: click (>=8.0.4,<9.0.0)
Requires-Dist: loguru (>=0.5.3,<0.6.0)
Requires-Dist: pydantic (>=1.9.0,<2.0.0)
